simple_oop/__init__.py
simple_oop/__main__.py
simple_oop/code_gen.py
simple_oop/config.py
simple_oop/discovery.py
simple_oop/node.py
simple_oop/version.py
simple_oop-2026.2.6.dist-info/METADATA
simple_oop-2026.2.6.dist-info/WHEEL
simple_oop-2026.2.6.dist-info/entry_points.txt
simple_oop-2026.2.6.dist-info/licenses/LICENSE.txt
simple_oop-2026.2.6.dist-info/RECORD
