Metadata-Version: 2.4
Name: simple-oop
Version: 2026.2.6
Summary: Placeholder description
Author-email: Guenthner <guenthner.jonathan@gmail.com>
License-File: LICENSE.txt
Classifier: License :: OSI Approved :: MIT License
Classifier: Operating System :: OS Independent
Classifier: Programming Language :: Python :: 3
Requires-Python: >=3.8
Requires-Dist: colorama
Requires-Dist: jinja2
Requires-Dist: pydantic
